src/__init__.py
src/cache.py
src/cli.py
src/config.py
src/languages.py
src/metrics.py
src/settings.py
src/agents/__init__.py
src/agents/agent.py
src/agents/personas.py
src/agents/redteam.py
src/db/__init__.py
src/db/storage.py
src/dna/__init__.py
src/dna/analyzer.py
src/dna/extractor.py
src/export/__init__.py
src/export/exporter.py
src/git/__init__.py
src/git/helpers.py
src/hooks/__init__.py
src/hooks/installer.py
src/models/__init__.py
src/models/review.py
src/orchestrator/__init__.py
src/orchestrator/debate.py
src/personas/__init__.py
src/personas/custom.py
src/personas/teams.py
src/predictions/__init__.py
src/predictions/market.py
src/predictions/models.py
src/predictions/storage.py
src/web/__init__.py
src/web/app.py
src/web/static/index.html
consensys-0.2.1.dist-info/METADATA
consensys-0.2.1.dist-info/WHEEL
consensys-0.2.1.dist-info/entry_points.txt
consensys-0.2.1.dist-info/top_level.txt
consensys-0.2.1.dist-info/RECORD
