Metadata-Version: 2.4
Name: consensys
Version: 0.2.1
Summary: Multi-agent code review with AI debate
Author-email: Consensys Team <consensys@example.com>
License: MIT
Project-URL: Homepage, https://github.com/noah-ing/consensys
Project-URL: Documentation, https://github.com/noah-ing/consensys#readme
Project-URL: Repository, https://github.com/noah-ing/consensys
Project-URL: Issues, https://github.com/noah-ing/consensys/issues
Keywords: code-review,ai,multi-agent,claude,anthropic
Classifier: Development Status :: 4 - Beta
Classifier: Environment :: Console
Classifier: Intended Audience :: Developers
Classifier: License :: OSI Approved :: MIT License
Classifier: Operating System :: OS Independent
Classifier: Programming Language :: Python :: 3
Classifier: Programming Language :: Python :: 3.9
Classifier: Programming Language :: Python :: 3.10
Classifier: Programming Language :: Python :: 3.11
Classifier: Programming Language :: Python :: 3.12
Classifier: Topic :: Software Development :: Quality Assurance
Classifier: Topic :: Software Development :: Testing
Requires-Python: >=3.9
Requires-Dist: anthropic>=0.18.0
Requires-Dist: click>=8.1.0
Requires-Dist: rich>=13.0.0
Requires-Dist: sqlite-utils>=3.35
Requires-Dist: python-dotenv>=1.0.0
Requires-Dist: tenacity>=8.2.0
Requires-Dist: pyyaml>=6.0
Provides-Extra: web
Requires-Dist: fastapi>=0.100.0; extra == "web"
Requires-Dist: uvicorn>=0.23.0; extra == "web"
Requires-Dist: websockets>=11.0; extra == "web"
Requires-Dist: jinja2>=3.1.0; extra == "web"
Provides-Extra: dev
Requires-Dist: pytest>=7.0; extra == "dev"
Requires-Dist: pytest-asyncio>=0.21.0; extra == "dev"
Requires-Dist: black; extra == "dev"
Requires-Dist: ruff; extra == "dev"
Provides-Extra: all
Requires-Dist: consensys[web]; extra == "all"
Requires-Dist: consensys[dev]; extra == "all"
